spotify_utils/__init__.py
spotify_utils/config.py
spotify_utils/main.py
spotify_utils/settings.toml
spotify_utils/src/__init__.py
spotify_utils/src/auth.py
spotify_utils/src/file_operations.py
spotify_utils/src/playlists.py
spotify_utils/src/user.py
spotify_utils/templates/playlists.html
spotify_utils-1.0.14.dist-info/LICENSE
spotify_utils-1.0.14.dist-info/METADATA
spotify_utils-1.0.14.dist-info/WHEEL
spotify_utils-1.0.14.dist-info/entry_points.txt
spotify_utils-1.0.14.dist-info/RECORD
