Metadata-Version: 2.3
Name: spotify-utils
Version: 1.0.14
Summary: An awesome and easy-to-use CLI for various Spotify® utility tasks
License: Apache-2.0
Keywords: spotify,CLI,utilities
Author: Fabian Eulitz
Author-email: dev@sustineo.de
Requires-Python: >=3.9,<4.0
Classifier: License :: OSI Approved :: Apache Software License
Classifier: Programming Language :: Python :: 3
Classifier: Programming Language :: Python :: 3.9
Classifier: Programming Language :: Python :: 3.10
Classifier: Programming Language :: Python :: 3.11
Classifier: Programming Language :: Python :: 3.12
Classifier: Programming Language :: Python :: 3.13
Requires-Dist: Jinja2 (>=3.1,<4.0)
Requires-Dist: dynaconf (>=3.2,<4.0)
Requires-Dist: spotipy (>=2.25,<3.0)
Requires-Dist: tabulate (>=0.9,<1.0)
Requires-Dist: typer (>=0.15,<1.0)
Project-URL: Repository, https://github.com/fabieu/spotify-utils
